{
    "$schema": "http://schema.management.azure.com/schemas/2015-01-01/deploymentTemplate.json#",
    "contentVersion": "1.0.0.0",
    "parameters": {
        "resourcesPrefix": {
            "type": "string"
        },
        "adDomainName": {
            "type": "string"
        },
        "adminUsername": {
            "type": "string"
        },
        "adminPassword": {
            "defaultValue": null,
            "type": "secureString"
        },
        "sqlServiceUserName": {
            "type": "string"
        },
        "sqlServicePassword": {
            "defaultValue": null,
            "type": "secureString"
        }
    },
    "variables": {
        "vm_dc01": "[concat(parameters('resourcesPrefix'),'-dc01')]",
        "vm_sql01": "[concat(parameters('resourcesPrefix'),'-sql01')]",
        "vm_sql02": "[concat(parameters('resourcesPrefix'),'-sql02')]",
        "vm_fsw01": "[concat(parameters('resourcesPrefix'),'-fsw01')]",

        "CreateFailOverClusterModulesURL": "https://github.com/pateixei/ptx-sqlAoCluster/raw/master/CreateSQLAoCluster-Step2.ps1.zip",
        "CreateFCConfigurationFunction": "CreateFailoverCluster.ps1\\CreateFailoverCluster",

        "ClusterName": "[concat(parameters('resourcesPrefix'),'-sqlAoFC')]",
        "sqlAlwaysOnEndpointName": "[concat(parameters('resourcesPrefix'),'-sqlAoEp')]",
        "sqlAlwaysOnAvailabilityGroupName": "[concat(parameters('resourcesPrefix'),'-sqlAoAG')]",
        "sqlAlwaysOnAvailabilityGroupListenerName": "[concat(parameters('resourcesPrefix'),'-sqlAoListener')]",
        "lbName": "[concat(parameters('resourcesPrefix'),'-ilb')]",
        "lbAddress": "172.16.1.10",
        "primaryReplica": "[variables('vm_sql02')]",
        "secondaryReplica": "[variables('vm_sql01')]",
        "dnsServerName": "[variables('vm_dc01')]",
        "databaseNames": [ "[concat(parameters('resourcesPrefix'),'-test-db01')]", "[concat(parameters('resourcesPrefix'),'-test-db02')]" ],
        "sharePath": "[concat('\\\\',variables('vm_dc01'),'\\sqlfsw')]"       
    },
    "resources": [
        {
            "type": "Microsoft.Compute/virtualMachines/extensions",
            "name": "[concat(variables('vm_sql02'),'/CreateFailoverCluster')]",
            "apiVersion": "2015-05-01-preview",
            "location": "[resourceGroup().location]",
            "properties": {
                "publisher": "Microsoft.Powershell",
                "type": "DSC",
                "typeHandlerVersion": "2.13",
                "autoUpgradeMinorVersion": true,
                "settings": {
                    "wmfVersion": "4.0",
                    "modulesUrl": "[variables('CreateFailOverClusterModulesURL')]",
                    "configurationFunction": "[variables('CreateFCConfigurationFunction')]",
                    "properties": {
                        "domainName": "[parameters('adDomainName')]",
                        "ClusterName": "[variables('clusterName')]",
                        "SharePath": "[variables('sharePath')]",
                        "Nodes":  [ 
                            "[variables('vm_sql01')]",
                            "[variables('vm_sql02')]"
                        ],
                        "sqlAlwaysOnAvailabilityGroupListenerPort": 1433,
                        "SqlAlwaysOnEndpointName": "[variables('sqlAlwaysOnEndpointName')]",
                        "SqlAlwaysOnAvailabilityGroupName": "[variables('sqlAlwaysOnAvailabilityGroupName')]",
                        "SqlAlwaysOnAvailabilityGroupListenerName": "[variables('sqlAlwaysOnAvailabilityGroupListenerName')]",
                        "LBName": "[variables('lbName')]",
                        "LBAddress": "[variables('lbAddress')]",
                        "PrimaryReplica": "[variables('primaryReplica')]",
                        "SecondaryReplica": "[variables('secondaryReplica')]",
                        "DatabaseNames": "[variables('databaseNames')]",
                        "DNSServerName": "[variables('dnsServerName')]",
                        "adminCreds": {
                            "userName": "[parameters('adminUserName')]",
                            "password": "PrivateSettingsRef:adminPassword"
                        },
                        "sQLServiceCreds": {
                            "userName": "[parameters('sqlServiceUserName')]",
                            "password": "PrivateSettingsRef:sqlServicePassword"
                        }
                    }
                },
                "protectedSettings": {
                    "items": {
                        "adminPassword": "[parameters('adminPassword')]",
                        "sqlServicePassword": "[parameters('sqlServicePassword')]"
                    }
                }
            }
        }
    ]
}